{
	"invalid-side": "&4Помилкова опція side.",
	"removed-queue": "&2Видалено з черги на створення магазину для продажу.",
	"added-queue": "&2Додано до черги на створення магазину для продажу. Торкніться там, де ви хочете його створити.",
	"removed-rm-queue": "&2Видалено з черги на видалення магазину для продажу.",
	"added-rm-queue": "&2Додано до черги на видалення магазину для продажу. Торкніться там, де ви хочете його видалити.",
	"sell-create-failed": "&4Невідома помилка створення магазину для продажу.",
	"sell-already-exist": "&4Магазин для продажу вже існує.",
	"sell-created": "&2Магазин для продажу успішно створено.",
	"sell-removed": "&2Магазин для продажу успішно видалено.",
	"no-permission-sell": "&4Ви не маєте права продавати тут речі.",
	"tap-again": "&eНатисніть знову щоб продати &2%2&e &b%1&e за &6%MONETARY_UNIT%%3&e.",
	"no-item": "Ви не маєте достатньо &4%1&r для продажу.",
	"failed-sell": "&4Невідома помилка продажу.",
	"sold-item": "Ви продали %2 &b%1&r за &6%MONETARY_UNIT%%3&r.",
	"sell-breaking-forbidden": "&4Ви не можете ламати магазини для продажу."
}
